LICENSE.txt
README.md
setup.cfg
setup.py
crawl/__init__.py
crawl/food.py
crawl/movie.py
crawl/music.py
crawl/news.py
crawl/remark.py
crawl/shop.py
crawltwj.egg-info/PKG-INFO
crawltwj.egg-info/SOURCES.txt
crawltwj.egg-info/dependency_links.txt
crawltwj.egg-info/top_level.txt