Metadata-Version: 2.1
Name: crawltwj
Version: 0.0.8.4
Summary: this is a crawl process
Author: twj
Classifier: License :: OSI Approved :: MIT License
Requires-Python: >=3.6
License-File: LICENSE.txt
